AUTHORS
ChangeLog
LICENSE
README.md
redispy-LICENSE
requirements.txt
setup.cfg
setup.py
test-requirements.txt
tox.ini
disq/__init__.py
disq/client.py
disq/parsers.py
disq/rolling_counter.py
disq.egg-info/PKG-INFO
disq.egg-info/SOURCES.txt
disq.egg-info/dependency_links.txt
disq.egg-info/not-zip-safe
disq.egg-info/pbr.json
disq.egg-info/requires.txt
disq.egg-info/top_level.txt
scripts/kill_disque
scripts/run_disque
tests/__init__.py
tests/conftest.py
tests/test_connection.py
tests/test_coversions.py
tests/test_job_benchmarks.py
tests/test_job_commands.py
tests/test_queue_commands.py
tests/test_rolling_counter.py
tests/test_server_commands.py