Metadata-Version: 1.1
Name: disq
Version: 0.0.4
Summary: Python Disque client (very very alpha, as is Disque itself)
Home-page: https://github.com/ryansb/disq
Author: Ryan Brown
Author-email: sb@ryansb.com
License: ASL2.0
Keywords: disque
Platform: UNKNOWN
Classifier: Natural Language :: English
Classifier: Operating System :: POSIX :: Linux
Classifier: License :: OSI Approved :: Apache Software License
Classifier: Programming Language :: Python :: 2.7
Classifier: Programming Language :: Python :: 3
Classifier: Programming Language :: Python :: 3.3
Classifier: Programming Language :: Python :: 3.4
